maisa/__init__.py
maisa/_base_client.py
maisa/_client.py
maisa/_compat.py
maisa/_constants.py
maisa/_exceptions.py
maisa/_files.py
maisa/_models.py
maisa/_qs.py
maisa/_resource.py
maisa/_response.py
maisa/_streaming.py
maisa/_types.py
maisa/_version.py
maisa/py.typed
maisa/_utils/__init__.py
maisa/_utils/_logs.py
maisa/_utils/_proxy.py
maisa/_utils/_streams.py
maisa/_utils/_sync.py
maisa/_utils/_transform.py
maisa/_utils/_typing.py
maisa/_utils/_utils.py
maisa/lib/.keep
maisa/resources/__init__.py
maisa/resources/kpu.py
maisa/resources/capabilities/__init__.py
maisa/resources/capabilities/capabilities.py
maisa/resources/capabilities/media.py
maisa/resources/file_interpreter/__init__.py
maisa/resources/file_interpreter/file_interpreter.py
maisa/resources/file_interpreter/from_audio.py
maisa/resources/file_interpreter/from_docx.py
maisa/resources/file_interpreter/from_html.py
maisa/resources/file_interpreter/from_image.py
maisa/resources/file_interpreter/from_pdf.py
maisa/resources/mainet/__init__.py
maisa/resources/mainet/mainet.py
maisa/resources/mainet/search.py
maisa/resources/models/__init__.py
maisa/resources/models/embeddings.py
maisa/resources/models/models.py
maisa/resources/models/rerank.py
maisa/types/__init__.py
maisa/types/capability_compare_params.py
maisa/types/capability_extract_params.py
maisa/types/capability_summarize_params.py
maisa/types/kpu_run_params.py
maisa/types/kpu_run_response.py
maisa/types/capabilities/__init__.py
maisa/types/capabilities/media_compare_params.py
maisa/types/capabilities/media_extract_params.py
maisa/types/capabilities/media_summarize_params.py
maisa/types/file_interpreter/__init__.py
maisa/types/file_interpreter/from_audio_create_params.py
maisa/types/file_interpreter/from_docx_create_params.py
maisa/types/file_interpreter/from_html_create_params.py
maisa/types/file_interpreter/from_image.py
maisa/types/file_interpreter/from_image_create_params.py
maisa/types/file_interpreter/from_pdf_create_params.py
maisa-0.1.0a4.dist-info/METADATA
maisa-0.1.0a4.dist-info/WHEEL
maisa-0.1.0a4.dist-info/licenses/LICENSE
maisa-0.1.0a4.dist-info/RECORD
